{"singlePage": ["link", "about"], "startSite": "10/26/1977", "filingNum": "", "onePageListNum": 10, "commentLabelColor": "#006b75", "yearColorList": ["#bc4c00", "#0969da", "#1f883d", "#A333D0"], "i18n": "CN", "themeMode": "fix", "dayTheme": "light", "nightTheme": "github-light", "urlMode": "issue", "script": "<script src='/fancyapps/dist/fancybox/fancybox.umd.js'></script>", "style": "", "head": "", "indexScript": "", "indexStyle": "", "bottomText": "", "showPostSource": 1, "iconList": {}, "UTC": 8, "rssSplit": "sentence", "exlink": {}, "needComment": 1, "allHead": "<script defer src='/blog/pluging/backtop.js'></script><script src='/blog/pluging/ArticleJs.min.js'></script><script src='/live2d/autoload.js'></script><script src='/blog/pluging/NumPagination.min.js'></script><script src='/blog/pluging/GmeekVercount_uv.min.js'></script><script src='/blog/pluging/customize.js'></script>", "title": "\u8001\u6797\u7b14\u8bb0", "subTitle": "<script>document.getElementById('subTitle').innerHTML = `<div id='divdown2' title=''></div>`;var interval = 1000; function ShowCountDown(year,month,day,divname) { var now = new Date(); var endDate = new Date(year, month-1, day); var leftTime=endDate.getTime()-now.getTime(); var leftsecond = parseInt(leftTime/1000); var day1=Math.floor(leftsecond/(60*60*24)); var hour=Math.floor((leftsecond-day1*24*60*60)/3600); var minute=Math.floor((leftsecond-day1*24*60*60-hour*3600)/60); var second=Math.floor(leftsecond-day1*24*60*60-hour*3600-minute*60); var cc = document.getElementById(divname); cc.innerHTML = `\u6691\u5047\u65f6\u95f4:`+year+`\u5e74`+month+`\u6708`+day+`\u65e5<br>\u8ddd\u4eca:`+day1+`\u5929`+hour+`\u5c0f\u65f6`+minute+`\u5206`+second+`\u79d2`; } window.setInterval(function(){ShowCountDown(2026,7,11,'divdown2');}, interval);</script>", "avatarUrl": "/blog/avatar.svg", "displayTitle": "\u8001\u6797\u7b14\u8bb0", "homeUrl": "https://linji1.github.io", "faviconUrl": "/blog/favicon.svg", "email": "saboha@163.com", "GMEEK_VERSION": "main", "postListJson": {}, "singeListJson": {}, "labelColorDict": {"about": "#aaaaaa", "bug": "#d73a4a", "documentation": "#0075ca", "duplicate": "#cfd3d7", "enhancement": "#a2eeef", "good first issue": "#7057ff", "help wanted": "#008672", "invalid": "#e4e669", "link": "#aaaaaa", "question": "#d876e3", "wontfix": "#ffffff", "\u4fe1\u606f\u79d1\u6280": "#0E8A16", "\u5b66\u6821\u5de5\u4f5c": "#1D76DB", "\u76f8\u5173\u901a\u77e5": "#736054", "\u7cd6\u5c3f\u75c5\u75c7": "#B60205", "\u7ee7\u7eed\u6559\u80b2": "#006B75", "\u95f2\u8a00\u788e\u8bed": "#920FFC"}, "ogImage": "/blog/avatar.svg", "primerCSS": "<link href='/blog/pluging/primer.min.css' rel='stylesheet' />", "prevUrl": "disabled", "nextUrl": "disabled"}